[
    {
        "depth_to_force_100mbps_migrations": 25, 
        "migration_info": {
            "Aggr PV": {
                "total_time": 1472.3970000743866, 
                "mig_years": {
                    "2019": "FTTB_UDWDM_100"
                }, 
                "final_data_rate": 100, 
                "mig_path": [
                    "ADSL", 
                    "FTTB_UDWDM_100", 
                    "FTTB_UDWDM_100", 
                    "FTTB_UDWDM_100", 
                    "FTTB_UDWDM_100", 
                    "FTTB_UDWDM_100", 
                    "FTTB_UDWDM_100", 
                    "FTTB_UDWDM_100", 
                    "FTTB_UDWDM_100", 
                    "FTTB_UDWDM_100", 
                    "FTTB_UDWDM_100", 
                    "FTTB_UDWDM_100", 
                    "FTTB_UDWDM_100", 
                    "FTTB_UDWDM_100", 
                    "FTTB_UDWDM_100"
                ], 
                "NPV_expected": 894186.4008467784, 
                "year_to_final_tech": 2019
            }, 
            "Likely PV": {
                "total_time": 1486.8719999790192, 
                "mig_years": {
                    "2019": "FTTB_UDWDM_50", 
                    "2028": "FTTB_UDWDM_100"
                }, 
                "final_data_rate": 100, 
                "mig_path": [
                    "ADSL", 
                    "FTTB_UDWDM_50", 
                    "FTTB_UDWDM_50", 
                    "FTTB_UDWDM_50", 
                    "FTTB_UDWDM_50", 
                    "FTTB_UDWDM_50", 
                    "FTTB_UDWDM_50", 
                    "FTTB_UDWDM_50", 
                    "FTTB_UDWDM_50", 
                    "FTTB_UDWDM_50", 
                    "FTTB_UDWDM_100", 
                    "FTTB_UDWDM_100", 
                    "FTTB_UDWDM_100", 
                    "FTTB_UDWDM_100", 
                    "FTTB_UDWDM_100"
                ], 
                "NPV_expected": 205667.48447944628, 
                "year_to_final_tech": 2028
            }, 
            "Cons PV": {
                "total_time": 1470.3680000305176, 
                "mig_years": {
                    "2019": "FTTB_UDWDM_50", 
                    "2028": "FTTB_UDWDM_100"
                }, 
                "final_data_rate": 100, 
                "mig_path": [
                    "ADSL", 
                    "FTTB_UDWDM_50", 
                    "FTTB_UDWDM_50", 
                    "FTTB_UDWDM_50", 
                    "FTTB_UDWDM_50", 
                    "FTTB_UDWDM_50", 
                    "FTTB_UDWDM_50", 
                    "FTTB_UDWDM_50", 
                    "FTTB_UDWDM_50", 
                    "FTTB_UDWDM_50", 
                    "FTTB_UDWDM_100", 
                    "FTTB_UDWDM_100", 
                    "FTTB_UDWDM_100", 
                    "FTTB_UDWDM_100", 
                    "FTTB_UDWDM_100"
                ], 
                "NPV_expected": 121624.67893030755, 
                "year_to_final_tech": 2028
            }
        }, 
        "is_ftth_and_force": false
    }, 
    {
        "depth_to_force_100mbps_migrations": 25, 
        "migration_info": {
            "Aggr PV": {
                "total_time": 1012.8910000324249, 
                "mig_years": {
                    "2019": "FTTB_UDWDM_50", 
                    "2028": "FTTH_UDWDM_100"
                }, 
                "final_data_rate": 100, 
                "mig_path": [
                    "ADSL", 
                    "FTTB_UDWDM_50", 
                    "FTTB_UDWDM_50", 
                    "FTTB_UDWDM_50", 
                    "FTTB_UDWDM_50", 
                    "FTTB_UDWDM_50", 
                    "FTTB_UDWDM_50", 
                    "FTTB_UDWDM_50", 
                    "FTTB_UDWDM_50", 
                    "FTTB_UDWDM_50", 
                    "FTTH_UDWDM_100", 
                    "FTTH_UDWDM_100", 
                    "FTTH_UDWDM_100", 
                    "FTTH_UDWDM_100", 
                    "FTTH_UDWDM_100"
                ], 
                "NPV_expected": 724635.7588715642, 
                "year_to_final_tech": 2028
            }, 
            "Likely PV": {
                "total_time": 1045.9880001544952, 
                "mig_years": {
                    "2019": "FTTB_UDWDM_50"
                }, 
                "final_data_rate": 50, 
                "mig_path": [
                    "ADSL", 
                    "FTTB_UDWDM_50", 
                    "FTTB_UDWDM_50", 
                    "FTTB_UDWDM_50", 
                    "FTTB_UDWDM_50", 
                    "FTTB_UDWDM_50", 
                    "FTTB_UDWDM_50", 
                    "FTTB_UDWDM_50", 
                    "FTTB_UDWDM_50", 
                    "FTTB_UDWDM_50", 
                    "FTTB_UDWDM_50", 
                    "FTTB_UDWDM_50", 
                    "FTTB_UDWDM_50", 
                    "FTTB_UDWDM_50", 
                    "FTTB_UDWDM_50", 
                    "FTTB_UDWDM_50"
                ], 
                "NPV_expected": 131472.5351461369, 
                "year_to_final_tech": 2033
            }, 
            "Cons PV": {
                "total_time": 1051.0179998874664, 
                "mig_years": {
                    "2019": "FTTB_UDWDM_50"
                }, 
                "final_data_rate": 50, 
                "mig_path": [
                    "ADSL", 
                    "FTTB_UDWDM_50", 
                    "FTTB_UDWDM_50", 
                    "FTTB_UDWDM_50", 
                    "FTTB_UDWDM_50", 
                    "FTTB_UDWDM_50", 
                    "FTTB_UDWDM_50", 
                    "FTTB_UDWDM_50", 
                    "FTTB_UDWDM_50", 
                    "FTTB_UDWDM_50", 
                    "FTTB_UDWDM_50", 
                    "FTTB_UDWDM_50", 
                    "FTTB_UDWDM_50", 
                    "FTTB_UDWDM_50", 
                    "FTTB_UDWDM_50", 
                    "FTTB_UDWDM_50"
                ], 
                "NPV_expected": 62959.584535250346, 
                "year_to_final_tech": 2033
            }
        }, 
        "is_ftth_and_force": true
    }, 
    {
        "depth_to_force_100mbps_migrations": 7, 
        "migration_info": {
            "Aggr PV": {
                "total_time": 1.4549999237060547, 
                "mig_years": {
                    "2019": "FTTB_UDWDM_100"
                }, 
                "final_data_rate": 100, 
                "mig_path": [
                    "ADSL", 
                    "FTTB_UDWDM_100", 
                    "FTTB_UDWDM_100", 
                    "FTTB_UDWDM_100", 
                    "FTTB_UDWDM_100", 
                    "FTTB_UDWDM_100", 
                    "FTTB_UDWDM_100", 
                    "FTTB_UDWDM_100", 
                    "FTTB_UDWDM_100", 
                    "FTTB_UDWDM_100", 
                    "FTTB_UDWDM_100", 
                    "FTTB_UDWDM_100", 
                    "FTTB_UDWDM_100", 
                    "FTTB_UDWDM_100", 
                    "FTTB_UDWDM_100"
                ], 
                "NPV_expected": 894186.4008467784, 
                "year_to_final_tech": 2019
            }, 
            "Likely PV": {
                "total_time": 1.5099999904632568, 
                "mig_years": {
                    "2019": "FTTB_UDWDM_100"
                }, 
                "final_data_rate": 100, 
                "mig_path": [
                    "ADSL", 
                    "FTTB_UDWDM_100", 
                    "FTTB_UDWDM_100", 
                    "FTTB_UDWDM_100", 
                    "FTTB_UDWDM_100", 
                    "FTTB_UDWDM_100", 
                    "FTTB_UDWDM_100", 
                    "FTTB_UDWDM_100", 
                    "FTTB_UDWDM_100", 
                    "FTTB_UDWDM_100", 
                    "FTTB_UDWDM_100", 
                    "FTTB_UDWDM_100", 
                    "FTTB_UDWDM_100", 
                    "FTTB_UDWDM_100", 
                    "FTTB_UDWDM_100"
                ], 
                "NPV_expected": 197548.05143960065, 
                "year_to_final_tech": 2019
            }, 
            "Cons PV": {
                "total_time": 1.4509999752044678, 
                "mig_years": {
                    "2019": "FTTB_UDWDM_100"
                }, 
                "final_data_rate": 100, 
                "mig_path": [
                    "ADSL", 
                    "FTTB_UDWDM_100", 
                    "FTTB_UDWDM_100", 
                    "FTTB_UDWDM_100", 
                    "FTTB_UDWDM_100", 
                    "FTTB_UDWDM_100", 
                    "FTTB_UDWDM_100", 
                    "FTTB_UDWDM_100", 
                    "FTTB_UDWDM_100", 
                    "FTTB_UDWDM_100", 
                    "FTTB_UDWDM_100", 
                    "FTTB_UDWDM_100", 
                    "FTTB_UDWDM_100", 
                    "FTTB_UDWDM_100", 
                    "FTTB_UDWDM_100"
                ], 
                "NPV_expected": 111906.8631759923, 
                "year_to_final_tech": 2019
            }
        }, 
        "is_ftth_and_force": false
    }, 
    {
        "depth_to_force_100mbps_migrations": 7, 
        "migration_info": {
            "Aggr PV": {
                "total_time": 0.9010000228881836, 
                "mig_years": {
                    "2024": "FTTH_XGPON_100", 
                    "2019": "FTTB_XGPON_50"
                }, 
                "final_data_rate": 100, 
                "mig_path": [
                    "ADSL", 
                    "FTTB_XGPON_50", 
                    "FTTB_XGPON_50", 
                    "FTTB_XGPON_50", 
                    "FTTB_XGPON_50", 
                    "FTTB_XGPON_50", 
                    "FTTH_XGPON_100", 
                    "FTTH_XGPON_100", 
                    "FTTH_XGPON_100", 
                    "FTTH_XGPON_100", 
                    "FTTH_XGPON_100", 
                    "FTTH_XGPON_100", 
                    "FTTH_XGPON_100", 
                    "FTTH_XGPON_100", 
                    "FTTH_XGPON_100"
                ], 
                "NPV_expected": 668477.3616308738, 
                "year_to_final_tech": 2024
            }, 
            "Likely PV": {
                "total_time": 0.9079999923706055, 
                "mig_years": {
                    "2025": "FTTH_XGPON_100", 
                    "2019": "FTTB_XGPON_50"
                }, 
                "final_data_rate": 100, 
                "mig_path": [
                    "ADSL", 
                    "FTTB_XGPON_50", 
                    "FTTB_XGPON_50", 
                    "FTTB_XGPON_50", 
                    "FTTB_XGPON_50", 
                    "FTTB_XGPON_50", 
                    "FTTB_XGPON_50", 
                    "FTTH_XGPON_100", 
                    "FTTH_XGPON_100", 
                    "FTTH_XGPON_100", 
                    "FTTH_XGPON_100", 
                    "FTTH_XGPON_100", 
                    "FTTH_XGPON_100", 
                    "FTTH_XGPON_100", 
                    "FTTH_XGPON_100"
                ], 
                "NPV_expected": -19927.266971657657, 
                "year_to_final_tech": 2025
            }, 
            "Cons PV": {
                "total_time": 0.9069998264312744, 
                "mig_years": {
                    "2025": "FTTH_XGPON_100", 
                    "2019": "FTTC_GPON_25", 
                    "2020": "FTTB_XGPON_50"
                }, 
                "final_data_rate": 100, 
                "mig_path": [
                    "ADSL", 
                    "FTTC_GPON_25", 
                    "FTTB_XGPON_50", 
                    "FTTB_XGPON_50", 
                    "FTTB_XGPON_50", 
                    "FTTB_XGPON_50", 
                    "FTTB_XGPON_50", 
                    "FTTH_XGPON_100", 
                    "FTTH_XGPON_100", 
                    "FTTH_XGPON_100", 
                    "FTTH_XGPON_100", 
                    "FTTH_XGPON_100", 
                    "FTTH_XGPON_100", 
                    "FTTH_XGPON_100", 
                    "FTTH_XGPON_100"
                ], 
                "NPV_expected": -105127.05100345358, 
                "year_to_final_tech": 2025
            }
        }, 
        "is_ftth_and_force": true
    }
]